[
  {
    "_id": "62b23c83496b5dc9b449c5ed",
    "state": "Activo",
    "patientDni": 13521062,
    "vaccine": "FiebreAmarilla",
    "vaccinationDate": "2022-10-14T04:00:00.000Z",
    "issueDate": "2022-06-21T21:42:21.159Z",
    "vaccinationCenter": "Polideportivo",
    "__v": 0
  },
  {
    "_id": "62b23cd8496b5dc9b449c5fa",
    "state": "Activo",
    "patientDni": 13521062,
    "vaccine": "Gripe",
    "vaccinationDate": "2022-07-12T04:00:00.000Z",
    "issueDate": "2022-06-21T21:42:21.159Z",
    "vaccinationCenter": "Polideportivo",
    "__v": 0
  },
  {
    "_id": "62b23cde496b5dc9b449c602",
    "state": "Finalizado",
    "patientDni": 13521062,
    "vaccine": "Covid",
    "vaccinationDate": "2021-12-21T04:00:00.000Z",
    "issueDate": "2022-06-21T21:42:21.159Z",
    "vaccinationCenter": "Corral贸n municipal",
    "__v": 0,
    "lot": "A24",
    "mark": "VACC"
  },
  {
    "_id": "62b23d23496b5dc9b449c611",
    "state": "Finalizado",
    "patientDni": 13521062,
    "vaccine": "Covid",
    "vaccinationDate": "2022-03-21T04:00:00.000Z",
    "issueDate": "2022-06-21T21:50:27.684Z",
    "vaccinationCenter": "Corral贸n municipal",
    "__v": 0,
    "lot": "A24",
    "mark": "VACC"
  },
  {
    "_id": "62b23d36496b5dc9b449c61f",
    "state": "Activo",
    "patientDni": 13521062,
    "vaccine": "Covid",
    "vaccinationDate": "2022-07-11T04:00:00.000Z",
    "issueDate": "2022-06-21T21:50:46.144Z",
    "vaccinationCenter": "Corral贸n municipal",
    "__v": 0
  },
  {
    "_id": "62b23da6496b5dc9b449c62b",
    "state": "Activo",
    "patientDni": 43521061,
    "vaccine": "Covid",
    "vaccinationDate": "2022-12-10T04:00:00.000Z",
    "issueDate": "2022-06-21T21:42:21.159Z",
    "vaccinationCenter": "Hospital 9 de Julio",
    "__v": 0
  },
  {
    "_id": "62b23daa496b5dc9b449c634",
    "state": "Activo",
    "patientDni": 43521061,
    "vaccine": "Gripe",
    "vaccinationDate": "2022-06-30T04:00:00.000Z",
    "issueDate": "2022-06-21T21:42:21.159Z",
    "vaccinationCenter": "Hospital 9 de Julio",
    "__v": 0
  },
  {
    "_id": "62b23deb496b5dc9b449c643",
    "state": "Activo",
    "patientDni": 43521060,
    "vaccine": "FiebreAmarilla",
    "vaccinationDate": "2022-06-23T04:00:00.000Z",
    "issueDate": "2022-06-21T21:42:21.159Z",
    "vaccinationCenter": "Hospital 9 de Julio",
    "__v": 0
  },
  {
    "_id": "62b23e08496b5dc9b449c64c",
    "state": "Activo",
    "patientDni": 43521060,
    "vaccine": "Gripe",
    "vaccinationDate": "2022-06-23T04:00:00.000Z",
    "issueDate": "2022-06-21T21:42:21.159Z",
    "vaccinationCenter": "Hospital 9 de Julio",
    "__v": 0
  },
  {
    "_id": "62b23e0c496b5dc9b449c654",
    "state": "Activo",
    "patientDni": 43521060,
    "vaccine": "Covid",
    "vaccinationDate": "2022-07-13T04:00:00.000Z",
    "issueDate": "2022-06-21T21:42:21.159Z",
    "vaccinationCenter": "Hospital 9 de Julio",
    "__v": 0
  },
  {
    "_id": "62b23e52496b5dc9b449c65f",
    "state": "Activo",
    "patientDni": 43521064,
    "vaccine": "FiebreAmarilla",
    "vaccinationDate": "2022-06-23T04:00:00.000Z",
    "issueDate": "2022-06-21T21:42:21.159Z",
    "vaccinationCenter": "Corral贸n municipal",
    "__v": 0
  },
  {
    "_id": "62b23ea5496b5dc9b449c668",
    "state": "Activo",
    "patientDni": 43521064,
    "vaccine": "Gripe",
    "vaccinationDate": "2022-06-23T04:00:00.000Z",
    "issueDate": "2022-06-21T21:42:21.159Z",
    "vaccinationCenter": "Hospital 9 de Julio",
    "__v": 0
  },
  {
    "_id": "62b23eaa496b5dc9b449c670",
    "state": "Finalizado",
    "patientDni": 43521064,
    "vaccine": "Covid",
    "vaccinationDate": "2022-05-15T04:00:00.000Z",
    "issueDate": "2022-06-21T21:42:21.159Z",
    "vaccinationCenter": "Polideportivo",
    "__v": 0,
    "lot": "A24",
    "mark": "VACC"
  },
  {
    "_id": "62b23f6f496b5dc9b449c68c",
    "state": "Activo",
    "patientDni": 53521062,
    "vaccine": "Gripe",
    "vaccinationDate": "2022-12-21T04:00:00.000Z",
    "issueDate": "2022-06-21T21:42:21.159Z",
    "vaccinationCenter": "Polideportivo",
    "__v": 0
  },
  {
    "_id": "62b23ff8496b5dc9b449c69b",
    "state": "Activo",
    "patientDni": 43521067,
    "vaccine": "Gripe",
    "vaccinationDate": "2022-12-21T04:00:00.000Z",
    "issueDate": "2022-06-21T21:42:21.159Z",
    "vaccinationCenter": "Hospital 9 de Julio",
    "__v": 0
  }
]
